usgs_riverdata/__init__.py
usgs_riverdata-0.1.2.dist-info/WHEEL
usgs_riverdata-0.1.2.dist-info/METADATA
usgs_riverdata-0.1.2.dist-info/RECORD
