Metadata-Version: 2.1
Name: usgs-riverdata
Version: 0.1.2
Summary: Pulls data from the USGS Water Data service
Home-page: https://github.com/wdfrench13/usgs-waterdata
License: Creative Commons Attribution Sharealike 3.0 Unported
Keywords: USGS,waterdata,river
Author: William French
Author-email: wdfrench13@gmail.com
Requires-Python: >=3.7,<4.0
Classifier: License :: Other/Proprietary License
Classifier: Programming Language :: Python :: 3
Classifier: Programming Language :: Python :: 3.10
Classifier: Programming Language :: Python :: 3.7
Classifier: Programming Language :: Python :: 3.8
Classifier: Programming Language :: Python :: 3.9
Project-URL: Repository, https://github.com/wdfrench13/usgs-waterdata
